ComputationalHypergraphDiscovery/_GraphDiscoveryMain.py
ComputationalHypergraphDiscovery/__init__.py
ComputationalHypergraphDiscovery/decision.py
ComputationalHypergraphDiscovery/helper_functions.py
ComputationalHypergraphDiscovery/interpolatory.py
ComputationalHypergraphDiscovery/non_interpolatory.py
ComputationalHypergraphDiscovery/util.py
ComputationalHypergraphDiscovery/Modes/__init__.py
ComputationalHypergraphDiscovery/Modes/container.py
ComputationalHypergraphDiscovery/Modes/kernels.py
ComputationalHypergraphDiscovery-2.0.0.dist-info/LICENSE
ComputationalHypergraphDiscovery-2.0.0.dist-info/METADATA
ComputationalHypergraphDiscovery-2.0.0.dist-info/WHEEL
ComputationalHypergraphDiscovery-2.0.0.dist-info/top_level.txt
ComputationalHypergraphDiscovery-2.0.0.dist-info/RECORD
