Metadata-Version: 2.1
Name: ComputationalHypergraphDiscovery
Version: 2.0.0
Summary: Implements the Computational Hypergraph Discovery algorithm
Author-email: Theo Bourdais <tbourdai@caltech.edu>, Houman Owhadi <owhadi@caltech.edu>, Pau Batlle Franch <pbatllef@caltech.edu>, Ricardo Baptista <rsb@caltech.edu>, Xianjin Yang <yxjmath@caltech.edu>
License: Apache License
Keywords: Machine Learning,Data Science,Applied Maths
Classifier: License :: OSI Approved :: Apache Software License
Classifier: Programming Language :: Python
Classifier: Programming Language :: Python :: 3
Requires-Python: >=3.9
License-File: LICENSE
Requires-Dist: matplotlib
Requires-Dist: networkx
Requires-Dist: numpy
Requires-Dist: scipy
